aiwaf/__init__.py
aiwaf/apps.py
aiwaf/blacklist_manager.py
aiwaf/decorators.py
aiwaf/middleware.py
aiwaf/middleware_logger.py
aiwaf/models.py
aiwaf/storage.py
aiwaf/trainer.py
aiwaf/utils.py
aiwaf/management/__init__.py
aiwaf/management/commands/__init__.py
aiwaf/management/commands/add_exemption.py
aiwaf/management/commands/add_ipexemption.py
aiwaf/management/commands/aiwaf_diagnose.py
aiwaf/management/commands/aiwaf_list.py
aiwaf/management/commands/aiwaf_logging.py
aiwaf/management/commands/aiwaf_reset.py
aiwaf/management/commands/check_dependencies.py
aiwaf/management/commands/clear_blacklist.py
aiwaf/management/commands/clear_cache.py
aiwaf/management/commands/debug_csv.py
aiwaf/management/commands/detect_and_train.py
aiwaf/management/commands/diagnose_blocking.py
aiwaf/management/commands/regenerate_model.py
aiwaf/management/commands/setup_models.py
aiwaf/management/commands/test_exemption.py
aiwaf/management/commands/test_exemption_fix.py
aiwaf/resources/model.pkl
aiwaf/templatetags/__init__.py
aiwaf/templatetags/aiwaf_tags.py
aiwaf-0.1.9.3.4.dist-info/licenses/LICENSE
aiwaf-0.1.9.3.4.dist-info/METADATA
aiwaf-0.1.9.3.4.dist-info/WHEEL
aiwaf-0.1.9.3.4.dist-info/top_level.txt
aiwaf-0.1.9.3.4.dist-info/RECORD
