Metadata-Version: 2.4
Name: aiwaf
Version: 0.1.9.3.4
Summary: AI-powered Web Application Firewall
Home-page: https://github.com/aayushgauba/aiwaf
Author: Aayush Gauba
Author-email: Aayush Gauba <gauba.aayush@gmail.com>
License: MIT
Requires-Python: >=3.8
License-File: LICENSE
Requires-Dist: Django>=3.2
Requires-Dist: numpy>=1.21
Requires-Dist: pandas>=1.3
Requires-Dist: scikit-learn<2.0,>=1.0
Requires-Dist: joblib>=1.1
Requires-Dist: packaging>=21.0
Requires-Dist: requests>=2.25.0
Dynamic: author
Dynamic: home-page
Dynamic: license-file
Dynamic: requires-python
